gender_api/__init__.py
gender_api/client.py
gender_api/country.py
gender_api/exceptions.py
gender_api/models.py
gender_api_client-1.0.0.dist-info/licenses/LICENSE
gender_api_client-1.0.0.dist-info/METADATA
gender_api_client-1.0.0.dist-info/WHEEL
gender_api_client-1.0.0.dist-info/top_level.txt
gender_api_client-1.0.0.dist-info/RECORD
