Metadata-Version: 2.4
Name: gender-api-client
Version: 1.0.0
Summary: A Python client for the Gender-API.com service.
Author-email: "Gender-API.com" <support@gender-api.com>
License: MIT License
Project-URL: Homepage, https://gender-api.com
Project-URL: Bug Tracker, https://github.com/gender-api/gender-api-client-python/issues
Classifier: Programming Language :: Python :: 3
Classifier: Programming Language :: Python :: 3.7
Classifier: Programming Language :: Python :: 3.8
Classifier: Programming Language :: Python :: 3.9
Classifier: Programming Language :: Python :: 3.10
Classifier: Programming Language :: Python :: 3.11
Classifier: Programming Language :: Python :: 3.12
Classifier: Programming Language :: Python :: 3.13
Classifier: License :: OSI Approved :: MIT License
Classifier: Operating System :: OS Independent
Requires-Python: >=3.7
License-File: LICENSE
Requires-Dist: requests
Requires-Dist: pydantic>=2.0.0
Provides-Extra: dev
Requires-Dist: pytest; extra == "dev"
Requires-Dist: requests-mock; extra == "dev"
Requires-Dist: ruff; extra == "dev"
Requires-Dist: mypy; extra == "dev"
Requires-Dist: types-requests; extra == "dev"
Dynamic: license-file
